kive/__init__.py
kive/exceptions.py
kive/memory.py
kive/models.py
kive/providers/__init__.py
kive/providers/base.py
kive/providers/cloud/__init__.py
kive/providers/cloud/base.py
kive/providers/cloud/cognee.py
kive/providers/cloud/mem0.py
kive/providers/cloud/memobase.py
kive/providers/cloud/memos.py
kive/providers/cloud/memu.py
kive/providers/cloud/supermemory.py
kive/providers/cloud/zep.py
kive/providers/local/__init__.py
kive/providers/local/base.py
kive/providers/local/cognee.py
kive/providers/local/graphiti.py
kive/providers/local/llm_bridge.py
kive/providers/local/mem0.py
kive/providers/local/memmachine.py
kive/providers/local/memos.py
kive/providers/local/memu.py
kive/providers/local/extensions/__init__.py
kive/providers/local/extensions/graphiti/__init__.py
kive/providers/local/extensions/graphiti/drivers/__init__.py
kive/providers/local/extensions/graphiti/drivers/kuzu_indices.py
kive/providers/local/extensions/graphiti/llm_clients/__init__.py
kive/providers/local/extensions/graphiti/llm_clients/bailian.py
kive/providers/local/extensions/memu/__init__.py
kive/providers/local/extensions/memu/persistence/__init__.py
kive/providers/local/extensions/memu/persistence/base.py
kive/providers/local/extensions/memu/persistence/postgres.py
kive/server/__init__.py
kive/server/schemas.py
kive/server/server.py
kive/utils/__init__.py
kive/utils/document.py
kive/utils/logger.py
kive-0.2.0.dist-info/licenses/LICENSE
kive-0.2.0.dist-info/METADATA
kive-0.2.0.dist-info/WHEEL
kive-0.2.0.dist-info/top_level.txt
kive-0.2.0.dist-info/RECORD
