Metadata-Version: 2.4
Name: kive
Version: 0.2.0
Summary: A lightweight memory service for AI applications with pluggable backends.
Author-email: Your Name <zhixiang.xzx@gmail.com>
License: MIT
Project-URL: Homepage, https://github.com/zhixiangxue/kive-ai
Project-URL: Documentation, https://github.com/zhixiangxue/kive-ai#readme
Project-URL: Repository, https://github.com/zhixiangxue/kive-ai
Project-URL: Issues, https://github.com/zhixiangxue/kive-ai/issues
Keywords: memory,ai,cognee,graphiti,llama-index
Classifier: Development Status :: 3 - Alpha
Classifier: Intended Audience :: Developers
Classifier: License :: OSI Approved :: MIT License
Classifier: Programming Language :: Python :: 3
Classifier: Programming Language :: Python :: 3.10
Classifier: Programming Language :: Python :: 3.11
Classifier: Programming Language :: Python :: 3.12
Requires-Python: >=3.8
License-File: LICENSE
Requires-Dist: pydantic>=2.0.0
Provides-Extra: client
Requires-Dist: httpx>=0.27.0; extra == "client"
Provides-Extra: server
Requires-Dist: fastapi>=0.110.0; extra == "server"
Requires-Dist: uvicorn[standard]>=0.29.0; extra == "server"
Requires-Dist: llama-index-core>=0.10.0; extra == "server"
Requires-Dist: loguru>=0.7.0; extra == "server"
Provides-Extra: zep-cloud
Requires-Dist: zep-cloud>=1.0.0; extra == "zep-cloud"
Provides-Extra: supermemory-cloud
Requires-Dist: supermemory>=1.0.0; extra == "supermemory-cloud"
Provides-Extra: cognee-cloud
Requires-Dist: cogwit-sdk>=0.4.1; extra == "cognee-cloud"
Provides-Extra: memobase-cloud
Requires-Dist: memobase>=1.0.0; extra == "memobase-cloud"
Provides-Extra: memos-cloud
Requires-Dist: chonkie==0.3.0; extra == "memos-cloud"
Requires-Dist: MemoryOS>=1.1.3; extra == "memos-cloud"
Provides-Extra: memu-cloud
Requires-Dist: memu-py>=0.1.0; extra == "memu-cloud"
Provides-Extra: mem0-cloud
Requires-Dist: mem0ai==1.0.1; extra == "mem0-cloud"
Provides-Extra: cognee-local
Requires-Dist: cognee==0.4.1; extra == "cognee-local"
Provides-Extra: graphiti-local
Requires-Dist: graphiti-core==0.24.1; extra == "graphiti-local"
Provides-Extra: mem0-local
Requires-Dist: mem0ai==1.0.1; extra == "mem0-local"
Requires-Dist: chromadb>=0.4.0; extra == "mem0-local"
Requires-Dist: kuzu>=0.7.0; extra == "mem0-local"
Provides-Extra: memmachine-local
Requires-Dist: pydantic>=2.11.7; extra == "memmachine-local"
Requires-Dist: neo4j>=5.28.2; extra == "memmachine-local"
Requires-Dist: asyncpg>=0.31.0; extra == "memmachine-local"
Requires-Dist: sqlalchemy>=2.0.43; extra == "memmachine-local"
Requires-Dist: openai>=1.104.2; extra == "memmachine-local"
Requires-Dist: sentence-transformers>=2.2.0; extra == "memmachine-local"
Provides-Extra: cloud
Requires-Dist: zep-cloud>=1.0.0; extra == "cloud"
Requires-Dist: supermemory>=1.0.0; extra == "cloud"
Requires-Dist: cogwit-sdk>=0.4.1; extra == "cloud"
Requires-Dist: memobase>=1.0.0; extra == "cloud"
Requires-Dist: memu-py>=0.1.0; extra == "cloud"
Requires-Dist: chonkie==0.3.0; extra == "cloud"
Requires-Dist: MemoryOS>=1.1.3; extra == "cloud"
Requires-Dist: mem0ai==1.0.1; extra == "cloud"
Provides-Extra: local
Requires-Dist: cognee==0.4.1; extra == "local"
Requires-Dist: graphiti-core==0.24.1; extra == "local"
Requires-Dist: mem0ai==1.0.1; extra == "local"
Requires-Dist: chromadb>=0.4.0; extra == "local"
Requires-Dist: kuzu>=0.7.0; extra == "local"
Requires-Dist: pydantic>=2.11.7; extra == "local"
Requires-Dist: neo4j>=5.28.2; extra == "local"
Requires-Dist: asyncpg>=0.31.0; extra == "local"
Requires-Dist: sqlalchemy>=2.0.43; extra == "local"
Requires-Dist: openai>=1.104.2; extra == "local"
Requires-Dist: sentence-transformers>=2.2.0; extra == "local"
Provides-Extra: dev
Requires-Dist: pytest>=7.0.0; extra == "dev"
Requires-Dist: pytest-asyncio>=0.21.0; extra == "dev"
Requires-Dist: black>=23.0.0; extra == "dev"
Requires-Dist: ruff>=0.1.0; extra == "dev"
Requires-Dist: mypy>=1.0.0; extra == "dev"
Provides-Extra: all
Requires-Dist: httpx>=0.27.0; extra == "all"
Requires-Dist: fastapi>=0.110.0; extra == "all"
Requires-Dist: uvicorn[standard]>=0.29.0; extra == "all"
Requires-Dist: llama-index-core>=0.10.0; extra == "all"
Requires-Dist: loguru>=0.7.0; extra == "all"
Requires-Dist: zep-cloud>=1.0.0; extra == "all"
Requires-Dist: supermemory>=1.0.0; extra == "all"
Requires-Dist: cogwit-sdk>=0.4.1; extra == "all"
Requires-Dist: memobase>=1.0.0; extra == "all"
Requires-Dist: memu-py>=0.1.0; extra == "all"
Requires-Dist: chonkie==0.3.0; extra == "all"
Requires-Dist: MemoryOS>=1.1.3; extra == "all"
Requires-Dist: cognee==0.4.1; extra == "all"
Requires-Dist: graphiti-core==0.24.1; extra == "all"
Requires-Dist: chromadb>=0.4.0; extra == "all"
Requires-Dist: kuzu>=0.7.0; extra == "all"
Requires-Dist: neo4j>=5.28.2; extra == "all"
Requires-Dist: asyncpg>=0.31.0; extra == "all"
Requires-Dist: pgvector>=0.3.0; extra == "all"
Requires-Dist: sqlalchemy>=2.0.43; extra == "all"
Requires-Dist: sentence-transformers>=2.2.0; extra == "all"
Requires-Dist: mem0ai==1.0.1; extra == "all"
Dynamic: license-file
